usagestats.py
usagestats-1.0.1.dist-info/LICENSE.txt
usagestats-1.0.1.dist-info/METADATA
usagestats-1.0.1.dist-info/WHEEL
usagestats-1.0.1.dist-info/top_level.txt
usagestats-1.0.1.dist-info/RECORD
