Metadata-Version: 2.1
Name: usagestats
Version: 1.0.1
Summary: Anonymous usage statistics collector
Home-page: https://github.com/remram44/usagestats
Author: Remi Rampin
Author-email: remirampin@gmail.com
Maintainer: Remi Rampin
Maintainer-email: remirampin@gmail.com
License: Apache License 2.0
Keywords: server,log,logging,usage,stats,statistics,collection,report
Platform: UNKNOWN
Classifier: Development Status :: 5 - Production/Stable
Classifier: Intended Audience :: Developers
Classifier: License :: OSI Approved :: Apache Software License
Classifier: Programming Language :: Python
Classifier: Topic :: Internet
Classifier: Topic :: Internet :: Log Analysis
Classifier: Topic :: Software Development
Classifier: Topic :: System :: Logging
Classifier: Topic :: Utilities
Requires-Dist: distro
Requires-Dist: requests
